pypgwrapper/__init__.py
pypgwrapper/postgres.py
pypgwrapper-1.0.0.dist-info/METADATA
pypgwrapper-1.0.0.dist-info/WHEEL
pypgwrapper-1.0.0.dist-info/top_level.txt
pypgwrapper-1.0.0.dist-info/RECORD
