Metadata-Version: 2.1
Name: pypgwrapper
Version: 1.0.0
Summary: Python wrapper for Postgres
Home-page: https://github.com/abeltavares/pypostgres
Author: Abel Tavares
Author-email: abelst9@gmail.com
License: BSD
Classifier: Topic :: Database
Classifier: Programming Language :: Python :: 3
Requires-Dist: psycopg2
Requires-Dist: tabulate
